LICENSE
MANIFEST.in
README.rst
setup.py
django_notifier.egg-info/PKG-INFO
django_notifier.egg-info/SOURCES.txt
django_notifier.egg-info/dependency_links.txt
django_notifier.egg-info/requires.txt
django_notifier.egg-info/top_level.txt
notifier/__init__.py
notifier/admin.py
notifier/backends.py
notifier/forms.py
notifier/managers.py
notifier/models.py
notifier/settings.py
notifier/shortcuts.py
notifier/tests.py
notifier/management/__init__.py
notifier/migrations/0001_initial.py
notifier/migrations/0002_auto__add_field_sentnotification_read.py
notifier/migrations/__init__.py
notifier/templates/notifier/test-notification_email_message.txt
notifier/templates/notifier/test-notification_email_subject.txt